axi4.v
module axi4(
    input wire clk,
    input wire reset,

    //AW
    input wire awvalid,
    input wire[31:0] awaddr,
    output reg awready,
    
    //W
    input wire wvalid,
    input wire[31:0] wdata,
    output reg wready,

    //RESPOSE B
    output reg bvalid,
    output reg[1:0] bresp,
    input wire bready,

    //AR
    input wire arvalid,
    input wire[31:0] araddr,
    output reg arready,

    //R
    output reg[31:0] rdata,
    output reg rvalid,
    output reg[1:0] rresp,
    input wire rready
);

    reg[31:0] my_reg [0:31];

    //FLAGS - latch
    reg aw_handshake;
    reg w_handshake;
    reg ar_handshake;

    reg [4:0]aw_index;
    reg [4:0]ar_index;
    integer i;

    always @(posedge clk) begin
        if(reset) begin
            awready <= 0;
            wready <= 0;
            bvalid <= 0;
            bresp <= 0;
            aw_handshake <= 0;
            w_handshake <= 0;

            arready <= 0;
            ar_handshake <= 0;
            rvalid <= 0;
            rdata <= 32'd0;
            rresp <= 2'b00;
            for (i = 0; i < 32; i = i + 1)
                my_reg[i] <= 32'd0;

        end else begin
            //AW
            if(~awready && awvalid && !aw_handshake) begin
                awready <= 1;
            end else begin
                awready <= 0;
            end

            if(!aw_handshake && awvalid && awready) begin
                aw_handshake <= 1;
                aw_index <= awaddr[6:2];
            end

            //W
            if(~wready && wvalid && !w_handshake) begin
                wready <= 1;
            end else begin
                wready <= 0;
            end

            if(!w_handshake && wvalid && wready) begin
                $display("The write address: %b",aw_index);
                w_handshake <= 1;
            end
            if(aw_handshake && w_handshake) begin
                my_reg[aw_index] <= wdata;
            end

            //B - response
            if(!bvalid && aw_handshake && w_handshake) begin
                bvalid <= 1;
                bresp <= 2'b00; //OKAY respose
            end

            //B - CLEAR
            if(bvalid && bready) begin
                bvalid <= 0;
                aw_handshake <= 0;
                w_handshake <= 0;
            end

            //AR
            if(~arready && arvalid && !ar_handshake) begin
                arready <= 1;
            end else begin
                arready <= 0;
            end
            
            //R
            if(!ar_handshake && arvalid && arready) begin
                ar_handshake <= 1;
                ar_index <= araddr[6:2];     //address
            end

            if(ar_handshake && !rvalid) begin
                $display("The Read address: %b",ar_index);
                rdata <= my_reg[ar_index];
                rvalid <= 1;
                rresp <= 2'b00;
            end

            if(rvalid && rready) begin
                rvalid <= 0;
                ar_handshake <= 0;
            end
        end 
    end

endmodule

master.v
module master(
    //MASTER INPUT
    input clk, 
    input reset,
    input wr_en,
    input rd_en,
    input [31:0] addr,
    input [31:0] wdata_in,

    //MASTER output
    output reg [31:0] rdata_out,
    output reg read_done, 
    output reg write_done,

    //AW
    output reg awvalid,
    output reg [31:0] awaddr,
    input awready,

    //W
    output reg wvalid,
    output reg [31:0] wdata,
    input wready,

    //B
    input bvalid,
    input [1:0] bresp,
    output reg bready,

    //AR
    output reg arvalid,
    output reg [31:0] araddr,
    input arready,

    //R
    output reg rready,
    input [31:0] rdata,
    input rvalid,
    input [1:0] rresp
);


    parameter W_IDLE  = 3'b000;
    parameter W_AW    = 3'b001;
    parameter W_W     = 3'b010;
    parameter W_B     = 3'b011;
    parameter W_DONE  = 3'b100;

    reg [2:0] w_state;

    parameter R_IDLE  = 2'b00;
    parameter R_AR    = 2'b01;
    parameter R_R     = 2'b10;
    parameter R_DONE  = 2'b11;

    reg [1:0] r_state;

    //INTERNAL LATCH
    reg [31:0] waddr_latch;
    reg [31:0] wdata_latch;
    reg [31:0] raddr_latch;

    always @(posedge clk) begin
        if(reset) begin
            awvalid     <= 0;
            wvalid      <= 0;
            bready      <= 0;
            write_done  <= 0;
            awaddr      <= 0;
            wdata       <= 0;
            w_state     <= W_IDLE;

            // Read channel reset
            arvalid     <= 0;
            rready      <= 0;
            read_done   <= 0;
            araddr      <= 0;
            r_state     <= R_IDLE;

            //LATCH
            waddr_latch <= 0;
            wdata_latch <= 0;
            raddr_latch <= 0;
        end else begin
            case(w_state)
                //case fsm write
                W_IDLE: begin
                    write_done <= 0;
                    if(wr_en) begin
                        waddr_latch <= addr;
                        wdata_latch <= wdata_in;
                        w_state <= W_AW;
                    end
                end
                W_AW: begin
                    awvalid <= 1;
                    awaddr <= waddr_latch;
                    if(awready) begin
                        awvalid <= 0;
                        w_state <= W_W;
                    end
                end
                W_W: begin
                    wvalid <= 1;
                    wdata <= wdata_latch;
                    if(wready) begin
                        wvalid <= 0;
                        bready <= 1;
                        w_state <= W_B;
                    end
                end
                W_B: begin
                    if(bvalid) begin
                        bready <= 0;
                        w_state <= W_DONE;
                    end
                end
                W_DONE: begin
                    write_done <= 1;
                    w_state <= W_IDLE;
                end
                default: w_state <= W_IDLE;
            endcase
            
            //----READ FSM----
            case(r_state)
                R_IDLE: begin
                    read_done <= 0;
                    if(rd_en) begin
                        raddr_latch <= addr;
                        r_state <= R_AR;
                    end
                end
                R_AR: begin
                    araddr <= raddr_latch;
                    arvalid <= 1;
                    if(arready) begin
                        arvalid <= 0;
                        rready <= 1;
                        r_state <= R_R;
                    end
                end
                R_R: begin
                    if(rvalid) begin
                        rdata_out <= rdata;
                        rready <= 0;
                        r_state <= R_DONE; 
                    end
                end
                R_DONE: begin
                    read_done <= 1;
                    r_state <= R_IDLE;
                end
                default: r_state <= R_IDLE;
            endcase
        end
    end
endmodule

top.v
`include "master.v"
`include "axi4.v"

module top (
    input clk,
    input reset,
    input wr_en,
    input rd_en,
    input [31:0] addr,
    input [31:0] wdata_in,
    output [31:0] rdata_out,
    output read_done,
    output write_done
);

    // AXI-Lite Interconnect signals
    wire awvalid, awready;
    wire [31:0] awaddr;

    wire wvalid, wready;
    wire [31:0] wdata;

    wire bvalid, bready;
    wire [1:0] bresp;

    wire arvalid, arready;
    wire [31:0] araddr;

    wire rvalid, rready;
    wire [31:0] rdata;
    wire [1:0] rresp;

    master m (
        .clk(clk),
        .reset(reset),
        .wr_en(wr_en),
        .rd_en(rd_en),
        .addr(addr),
        .wdata_in(wdata_in),
        .rdata_out(rdata_out),
        .read_done(read_done),
        .write_done(write_done),
        .awvalid(awvalid),
        .awaddr(awaddr),
        .awready(awready),
        .wvalid(wvalid),
        .wdata(wdata),
        .wready(wready),
        .bvalid(bvalid),
        .bresp(bresp),
        .bready(bready),
        .arvalid(arvalid),
        .araddr(araddr),
        .arready(arready),
        .rready(rready),
        .rdata(rdata),
        .rvalid(rvalid),
        .rresp(rresp)
    );

    axi4 s (
        .clk(clk),
        .reset(reset),
        .awvalid(awvalid),
        .awaddr(awaddr),
        .awready(awready),
        .wvalid(wvalid),
        .wdata(wdata),
        .wready(wready),
        .bvalid(bvalid),
        .bresp(bresp),
        .bready(bready),
        .arvalid(arvalid),
        .araddr(araddr),
        .arready(arready),
        .rdata(rdata),
        .rvalid(rvalid),
        .rresp(rresp),
        .rready(rready)
    );

endmodule

top_tb.v
`timescale 1ns/1ns
`include "top.v"

module top_tb;

    reg clk = 0;
    reg reset = 1;
    reg wr_en = 0;
    reg rd_en = 0;
    reg [31:0] addr = 0;
    reg [31:0] wdata_in = 0;
    wire [31:0] rdata_out;
    wire read_done;
    wire write_done;

    top DUT (
        .clk(clk),
        .reset(reset),
        .wr_en(wr_en),
        .rd_en(rd_en),
        .addr(addr),
        .wdata_in(wdata_in),
        .rdata_out(rdata_out),
        .read_done(read_done),
        .write_done(write_done)
    );

    always #5 clk = ~clk;

    initial begin
        reset = 1;
        $dumpfile("top_tb.vcd");
        $dumpvars(0, top_tb);

        #20 reset = 0;

        // WRITE: addr=0x00000010, data=0xABCD1234
        @(posedge clk);
        addr <= 32'h00000010;
        wdata_in <= 32'hCEEB2006;
        wr_en <= 1;

        @(posedge clk);
        wr_en <= 0;

        wait(write_done);
        $display("✅ Write complete at %0t", $time);

        // READ from addr=0x00000010
        @(posedge clk);
        addr <= 32'h00000010;
        rd_en <= 1;

        @(posedge clk);
        rd_en <= 0;

        wait(read_done);
        $display("✅ Read complete at %0t, rdata_out = 0x%08x", $time, rdata_out);

        #20 $finish;
    end

endmodule

top_tb.vcd
$date
	Wed Jul 30 19:58:01 2025
$end
$version
	Icarus Verilog
$end
$timescale
	1ns
$end
$scope module top_tb $end
$var wire 1 ! write_done $end
$var wire 1 " read_done $end
$var wire 32 # rdata_out [31:0] $end
$var reg 32 $ addr [31:0] $end
$var reg 1 % clk $end
$var reg 1 & rd_en $end
$var reg 1 ' reset $end
$var reg 32 ( wdata_in [31:0] $end
$var reg 1 ) wr_en $end
$scope module DUT $end
$var wire 32 * addr [31:0] $end
$var wire 1 % clk $end
$var wire 1 & rd_en $end
$var wire 1 ' reset $end
$var wire 32 + wdata_in [31:0] $end
$var wire 1 ) wr_en $end
$var wire 1 , wvalid $end
$var wire 1 ! write_done $end
$var wire 1 - wready $end
$var wire 32 . wdata [31:0] $end
$var wire 1 / rvalid $end
$var wire 2 0 rresp [1:0] $end
$var wire 1 1 rready $end
$var wire 1 " read_done $end
$var wire 32 2 rdata_out [31:0] $end
$var wire 32 3 rdata [31:0] $end
$var wire 1 4 bvalid $end
$var wire 2 5 bresp [1:0] $end
$var wire 1 6 bready $end
$var wire 1 7 awvalid $end
$var wire 1 8 awready $end
$var wire 32 9 awaddr [31:0] $end
$var wire 1 : arvalid $end
$var wire 1 ; arready $end
$var wire 32 < araddr [31:0] $end
$scope module m $end
$var wire 32 = addr [31:0] $end
$var wire 1 % clk $end
$var wire 1 & rd_en $end
$var wire 1 ' reset $end
$var wire 32 > wdata_in [31:0] $end
$var wire 1 ) wr_en $end
$var wire 1 - wready $end
$var wire 1 / rvalid $end
$var wire 2 ? rresp [1:0] $end
$var wire 32 @ rdata [31:0] $end
$var wire 1 4 bvalid $end
$var wire 2 A bresp [1:0] $end
$var wire 1 8 awready $end
$var wire 1 ; arready $end
$var parameter 2 B R_AR $end
$var parameter 2 C R_DONE $end
$var parameter 2 D R_IDLE $end
$var parameter 2 E R_R $end
$var parameter 3 F W_AW $end
$var parameter 3 G W_B $end
$var parameter 3 H W_DONE $end
$var parameter 3 I W_IDLE $end
$var parameter 3 J W_W $end
$var reg 32 K araddr [31:0] $end
$var reg 1 : arvalid $end
$var reg 32 L awaddr [31:0] $end
$var reg 1 7 awvalid $end
$var reg 1 6 bready $end
$var reg 2 M r_state [1:0] $end
$var reg 32 N raddr_latch [31:0] $end
$var reg 32 O rdata_out [31:0] $end
$var reg 1 " read_done $end
$var reg 1 1 rready $end
$var reg 3 P w_state [2:0] $end
$var reg 32 Q waddr_latch [31:0] $end
$var reg 32 R wdata [31:0] $end
$var reg 32 S wdata_latch [31:0] $end
$var reg 1 ! write_done $end
$var reg 1 , wvalid $end
$upscope $end
$scope module s $end
$var wire 32 T araddr [31:0] $end
$var wire 1 : arvalid $end
$var wire 32 U awaddr [31:0] $end
$var wire 1 7 awvalid $end
$var wire 1 6 bready $end
$var wire 1 % clk $end
$var wire 1 ' reset $end
$var wire 1 1 rready $end
$var wire 32 V wdata [31:0] $end
$var wire 1 , wvalid $end
$var reg 1 W ar_handshake $end
$var reg 5 X ar_index [4:0] $end
$var reg 1 ; arready $end
$var reg 1 Y aw_handshake $end
$var reg 5 Z aw_index [4:0] $end
$var reg 1 8 awready $end
$var reg 2 [ bresp [1:0] $end
$var reg 1 4 bvalid $end
$var reg 32 \ rdata [31:0] $end
$var reg 2 ] rresp [1:0] $end
$var reg 1 / rvalid $end
$var reg 1 ^ w_handshake $end
$var reg 1 - wready $end
$var integer 32 _ i [31:0] $end
$upscope $end
$upscope $end
$upscope $end
$enddefinitions $end
$comment Show the parameter values. $end
$dumpall
b10 J
b0 I
b100 H
b11 G
b1 F
b10 E
b0 D
b11 C
b1 B
$end
#0
$dumpvars
bx _
x^
bx ]
bx \
bx [
bx Z
xY
bx X
xW
bx V
bx U
bx T
bx S
bx R
bx Q
bx P
bx O
bx N
bx M
bx L
bx K
bx A
bx @
bx ?
b0 >
b0 =
bx <
x;
x:
bx 9
x8
x7
x6
bx 5
x4
bx 3
bx 2
x1
bx 0
x/
bx .
x-
x,
b0 +
b0 *
0)
b0 (
1'
0&
0%
b0 $
bx #
x"
x!
$end
#5
b0 N
b0 S
b0 Q
b0 M
b0 <
b0 K
b0 T
0"
01
0:
b0 P
b0 .
b0 R
b0 V
b0 9
b0 L
b0 U
0!
06
0,
07
b0 0
b0 ?
b0 ]
b0 3
b0 @
b0 \
0/
0W
0;
0^
0Y
b0 5
b0 A
b0 [
04
0-
08
b100000 _
1%
#10
0%
#15
b100000 _
1%
#20
0%
0'
#25
1)
b11001110111010110010000000000110 (
b11001110111010110010000000000110 +
b11001110111010110010000000000110 >
b10000 $
b10000 *
b10000 =
1%
#30
0%
#35
0)
b1 P
b11001110111010110010000000000110 S
b10000 Q
1%
#40
0%
#45
b10000 9
b10000 L
b10000 U
17
1%
#50
0%
#55
18
1%
#60
0%
#65
b10 P
07
b100 Z
1Y
08
1%
#70
0%
#75
b11001110111010110010000000000110 .
b11001110111010110010000000000110 R
b11001110111010110010000000000110 V
1,
1%
#80
0%
#85
1-
1%
#90
0%
#95
1^
0-
b11 P
16
0,
1%
#100
0%
#105
14
1%
#110
0%
#115
0^
0Y
04
b100 P
06
1%
#120
0%
#125
b0 P
1!
1%
#130
0%
#135
0!
1&
1%
#140
0%
#145
0&
b1 M
b10000 N
1%
#150
0%
#155
1:
b10000 <
b10000 K
b10000 T
1%
#160
0%
#165
1;
1%
#170
0%
#175
b100 X
1W
0;
b10 M
11
0:
1%
#180
0%
#185
1/
b11001110111010110010000000000110 3
b11001110111010110010000000000110 @
b11001110111010110010000000000110 \
1%
#190
0%
#195
0W
0/
b11 M
01
b11001110111010110010000000000110 #
b11001110111010110010000000000110 2
b11001110111010110010000000000110 O
1%
#200
0%
#205
b0 M
1"
1%
#210
0%
#215
0"
1%
